graph_onedrive/__init__.py
graph_onedrive/__main__.py
graph_onedrive/_cli.py
graph_onedrive/_config.py
graph_onedrive/_decorators.py
graph_onedrive/_main.py
graph_onedrive/_manager.py
graph_onedrive/_onedrive.py
graph_onedrive/py.typed
graph_onedrive-0.5.0.dist-info/licenses/LICENSE
graph_onedrive-0.5.0.dist-info/METADATA
graph_onedrive-0.5.0.dist-info/WHEEL
graph_onedrive-0.5.0.dist-info/entry_points.txt
graph_onedrive-0.5.0.dist-info/top_level.txt
graph_onedrive-0.5.0.dist-info/RECORD
