Metadata-Version: 2.4
Name: graph_onedrive
Version: 0.5.0
Summary: Perform simple tasks on OneDrive through the Graph API.
Home-page: https://github.com/dariobauer/graph-onedrive
Author: Dario Bauer
Author-email: dariobauer@duck.com
License: BSD-3-Clause
Project-URL: Documentation, https://github.com/dariobauer/graph-onedrive/blob/main/docs/DOCUMENTATION.md
Project-URL: Issue Tracker, https://github.com/dariobauer/graph-onedrive/issues
Project-URL: Changes, https://github.com/dariobauer/graph-onedrive/blob/main/CHANGES.md
Project-URL: Source Code, https://github.com/dariobauer/graph-onedrive
Keywords: onedrive,graph,microsoft
Classifier: Development Status :: 3 - Alpha
Classifier: Intended Audience :: Developers
Classifier: Operating System :: OS Independent
Classifier: Programming Language :: Python
Classifier: Programming Language :: Python :: 3
Classifier: Programming Language :: Python :: 3 :: Only
Requires-Python: >=3.9
License-File: LICENSE
Requires-Dist: aiofiles
Requires-Dist: httpx
Provides-Extra: toml
Requires-Dist: toml; extra == "toml"
Provides-Extra: yaml
Requires-Dist: pyyaml; extra == "yaml"
Dynamic: license-file
